bmlab/__init__.py
bmlab/_version.py
bmlab/_version_save.py
bmlab/constants.py
bmlab/controllers.py
bmlab/file.py
bmlab/fits.py
bmlab/geometry.py
bmlab/image.py
bmlab/serializer.py
bmlab/session.py
bmlab/utils.py
bmlab/export/__init__.py
bmlab/export/brillouin_export.py
bmlab/export/fluorescence_combined_export.py
bmlab/export/fluorescence_export.py
bmlab/models/__init__.py
bmlab/models/calibration_model.py
bmlab/models/evaluation_model.py
bmlab/models/extraction_model.py
bmlab/models/orientation.py
bmlab/models/peak_selection_model.py
bmlab/models/regions.py
bmlab/models/setup.py
bmlab-0.11.0.dist-info/LICENSE
bmlab-0.11.0.dist-info/METADATA
bmlab-0.11.0.dist-info/WHEEL
bmlab-0.11.0.dist-info/top_level.txt
bmlab-0.11.0.dist-info/RECORD
