Metadata-Version: 2.1
Name: bmlab
Version: 0.11.0
Summary: Library for Brillouin microscopy data analysis
Home-page: https://github.com/BrillouinMicroscopy/bmlab
Author: bmlab developers
Author-email: dev@craban.de
License: GPL v3
Keywords: Brillouin microscopy
Platform: ALL
Classifier: Operating System :: OS Independent
Classifier: Programming Language :: Python :: 3
Classifier: Topic :: Scientific/Engineering :: Visualization
Classifier: Intended Audience :: Science/Research
Requires-Python: >=3.10
License-File: LICENSE
Requires-Dist: h5py>=2.10.0
Requires-Dist: matplotlib
Requires-Dist: numpy>=1.17.0
Requires-Dist: packaging>=20.8
Requires-Dist: pillow
Requires-Dist: pytest
Requires-Dist: pytest-mock
Requires-Dist: scikit-image>=0.19.0
Requires-Dist: scipy
Requires-Dist: shapely>=1.8.2
